Week2-BabySoC Fundamentals & Functional modeling/Day 2 - Task 3  Simulation & Verification/ALU.v
module ALU(
    input [3:0] A,
    input [3:0] B,
    input [2:0] ALU_Sel,
    output reg [3:0] ALU_Out
);
    always @(*) begin
        case(ALU_Sel)
            3'b000: ALU_Out = A + B;
            3'b001: ALU_Out = A - B;
            3'b010: ALU_Out = A & B;
            3'b011: ALU_Out = A | B;
            default: ALU_Out = 4'b0000;
        endcase
    end
endmodule

Week2-BabySoC Fundamentals & Functional modeling/Day 2 - Task 3  Simulation & Verification/RegisterFile.v
module RegisterFile(
    input clk,
    input [1:0] ReadReg1,
    input [1:0] ReadReg2,
    input [1:0] WriteReg,
    input [3:0] WriteData,
    input RegWrite,
    output [3:0] ReadData1,
    output [3:0] ReadData2
);
    reg [3:0] regfile [3:0];

    assign ReadData1 = regfile[ReadReg1];
    assign ReadData2 = regfile[ReadReg2];

    always @(posedge clk) begin
        if(RegWrite)
            regfile[WriteReg] <= WriteData;
    end
endmodule

ProgramCounter.v
module ProgramCounter(
    input clk,
    input reset,
    output reg [3:0] PC
);
    always @(posedge clk or posedge reset) begin
        if(reset)
            PC <= 4'b0000;
        else
            PC <= PC + 1;
    end
endmodule

BabySoC.v
module BabySoC(
    input clk,
    input reset,
    output [3:0] ALU_Result
);
    wire [3:0] PC_Out;
    wire [3:0] Read1, Read2;

    ProgramCounter PC(.clk(clk), .reset(reset), .PC(PC_Out));
    RegisterFile RF(.clk(clk), .ReadReg1(2'b00), .ReadReg2(2'b01), .WriteReg(2'b10),
                    .WriteData(ALU_Result), .RegWrite(1'b1), .ReadData1(Read1), .ReadData2(Read2));
    ALU alu(.A(Read1), .B(Read2), .ALU_Sel(3'b000), .ALU_Out(ALU_Result));
endmodule

BabySoC_tb.v
`timescale 1ns/1ps

module baby_soc_tb;

    // Inputs to BabySoC
    reg clk;
    reg reset;

    // Outputs from BabySoC
    wire [3:0] ALU_Result;

    // Instantiate the top module (BabySoC)
    BabySoC uut (
        .clk(clk),
        .reset(reset),
        .ALU_Result(ALU_Result)
    );

    // Clock generation: toggle every 5 time units
    initial clk = 0;
    always #5 clk = ~clk;

    // Simulation sequence
    initial begin
        // Generate waveform file
        $dumpfile("baby_soc.vcd");
        $dumpvars(0, baby_soc_tb);

        // Apply reset
        reset = 1;
        #10 reset = 0;

        // Run simulation for some time
        #100 $finish;  // End simulation
    end

endmodule

Week2-BabySoC Fundamentals & Functional modeling/Programmings/baby_soc.vcd
$date
	Thu Oct 02 15:43:39 2025
$end
$version
	Icarus Verilog
$end
$timescale
	1ps
$end
$scope module baby_soc_tb $end
$var wire 4 ! ALU_Result [3:0] $end
$var reg 1 " clk $end
$var reg 1 # reset $end
$scope module uut $end
$var wire 1 " clk $end
$var wire 1 # reset $end
$var wire 4 $ Read2 [3:0] $end
$var wire 4 % Read1 [3:0] $end
$var wire 4 & PC_Out [3:0] $end
$var wire 4 ' ALU_Result [3:0] $end
$scope module PC $end
$var wire 1 " clk $end
$var wire 1 # reset $end
$var reg 4 ( PC [3:0] $end
$upscope $end
$scope module RF $end
$var wire 4 ) ReadData1 [3:0] $end
$var wire 4 * ReadData2 [3:0] $end
$var wire 2 + ReadReg1 [1:0] $end
$var wire 2 , ReadReg2 [1:0] $end
$var wire 1 - RegWrite $end
$var wire 2 . WriteReg [1:0] $end
$var wire 1 " clk $end
$var wire 4 / WriteData [3:0] $end
$upscope $end
$scope module alu $end
$var wire 4 0 A [3:0] $end
$var wire 3 1 ALU_Sel [2:0] $end
$var wire 4 2 B [3:0] $end
$var reg 4 3 ALU_Out [3:0] $end
$upscope $end
$upscope $end
$upscope $end
$enddefinitions $end
$comment Show the parameter values. $end
$dumpall
$end
#0
$dumpvars
bx 3
bx 2
b0 1
bx 0
bx /
b10 .
1-
b1 ,
b0 +
bx *
bx )
b0 (
bx '
b0 &
bx %
bx $
1#
0"
bx !
$end
#5000
1"
#10000
0"
0#
#15000
b1 &
b1 (
1"
#20000
0"
#25000
b10 &
b10 (
1"
#30000
0"
#35000
b11 &
b11 (
1"
#40000
0"
#45000
b100 &
b100 (
1"
#50000
0"
#55000
b101 &
b101 (
1"
#60000
0"
#65000
b110 &
b110 (
1"
#70000
0"
#75000
b111 &
b111 (
1"
#80000
0"
#85000
b1000 &
b1000 (
1"
#90000
0"
#95000
b1001 &
b1001 (
1"
#100000
0"
#105000
b1010 &
b1010 (
1"
